mp_throttle/__init__.py
mp_throttle/throttle.py
mp_throttle-0.0.5.dist-info/METADATA
mp_throttle-0.0.5.dist-info/RECORD
mp_throttle-0.0.5.dist-info/WHEEL
mp_throttle-0.0.5.dist-info/top_level.txt
