Metadata-Version: 2.1
Name: mp-throttle
Version: 0.0.5
Summary: Package to monitor and throttle multiple processes or threads.
Home-page: https://github.com/elpunkt/mp_throttle
Author: Lucas Langholf
Author-email: lucas@elpunkt.eu
License: UNKNOWN
Platform: UNKNOWN
Classifier: Programming Language :: Python :: 3
Classifier: Programming Language :: Python :: 3.5
Classifier: License :: OSI Approved :: MIT License
Classifier: Intended Audience :: Developers
